embr/__tests__/test_embr_advanced.py
embr/__tests__/test_embr_basic.py
embr/__tests__/test_embr_reducers.py
embr/cache_utils/.gitignore
embr/cache_utils/__tests__/test_context_cache.py
embr/cache_utils/__tests__/test_lru_mongodb.py
embr/cache_utils/context_cache.py
embr/cache_utils/lru_cache.py
embr/cache_utils/mongodb_cache.py
embr/cache_utils/pickle_cache.py
embr/embr.py
embr/parse_utils.py
embr/reducers.py
embr/roles.py
embr-0.0.1.dist-info/LICENSE
embr-0.0.1.dist-info/WHEEL
embr-0.0.1.dist-info/METADATA
embr-0.0.1.dist-info/RECORD
