Metadata-Version: 2.1
Name: embr
Version: 0.0.1
Summary: Natural Language Differential Programming
License: LICENSE
Author: Ge Yang
Author-email: ge.ike.yang@gmail.com
Requires-Python: >=3.9,<4.0
Classifier: License :: Other/Proprietary License
Classifier: Programming Language :: Python :: 3
Classifier: Programming Language :: Python :: 3.9
Classifier: Programming Language :: Python :: 3.10
Classifier: Programming Language :: Python :: 3.11
